modena/Strategy.py
modena/SurrogateModel.py
modena/__init__.py
modena/bin/twoTanksFullProblem
modena/include/modena/fmodena.mod
modena/include/modena/function.h
modena/include/modena/global.h
modena/include/modena/indexset.h
modena/include/modena/inline.h
modena/include/modena/inputsoutputs.h
modena/include/modena/model.h
modena/include/modena/modena.h
modena/include/modena/modenaModel.H
modena/lib/cmake/modena/CheckCInline.cmake
modena/lib/cmake/modena/FindLTDL.cmake
modena/lib/cmake/modena/FindMODENA.cmake
modena/lib/cmake/modena/MODENAConfig.cmake
modena/lib/cmake/modena/MODENAConfigVersion.cmake
modena/lib/cmake/modena/MODENATargets-debug.cmake
modena/lib/cmake/modena/MODENATargets.cmake
modena/lib/modena/libfmodena.so
modena/lib/modena/libmodena.so
modena/lib/modena/libmodena.so.1
modena/lib/modena/libmodena.so.1.0
modena/lib/pkgconfig/libmodena.pc
modena-0.0.3.dist-info/LICENSE
modena-0.0.3.dist-info/METADATA
modena-0.0.3.dist-info/WHEEL
modena-0.0.3.dist-info/top_level.txt
modena-0.0.3.dist-info/RECORD
