Metadata-Version: 2.1
Name: modena
Version: 0.0.3
Summary: Simulation framework application facilitating     simulation of interconnected models
License-File: LICENSE
Requires-Dist: blessings
Requires-Dist: decorator
Requires-Dist: mongoengine
Requires-Dist: numpy
Requires-Dist: Pillow
Requires-Dist: pymongo
Requires-Dist: rpy2
Requires-Dist: scipy
Requires-Dist: scour
Requires-Dist: singledispatch
Requires-Dist: six
Requires-Dist: sqlalchemy
Requires-Dist: fireworks
